hibachi/__init__.py
hibachi/criteria.py
hibachi/penalties.py
hibachi/rankers.py
hibachi/utils.py
test/__init__.py
test/test_criteria.py
test/test_rankers.py
test/test_utils.py
hibachi-0.0.1.dist-info/LICENSE.md
hibachi-0.0.1.dist-info/METADATA
hibachi-0.0.1.dist-info/WHEEL
hibachi-0.0.1.dist-info/top_level.txt
hibachi-0.0.1.dist-info/RECORD
