Metadata-Version: 2.1
Name: hibachi
Version: 0.0.1
Summary: Feature selection methods for PyTorch
Home-page: https://github.com/bveeramani/hibachi
Author: Balaji Veeramani
Author-email: bveeramani@berkeley.edu
License: UNKNOWN
Platform: UNKNOWN
Classifier: Programming Language :: Python :: 3
Classifier: License :: OSI Approved :: Apache Software License
Classifier: Operating System :: OS Independent
